fasterpc/__init__.py
fasterpc/connection_manager.py
fasterpc/logger.py
fasterpc/rpc_channel.py
fasterpc/rpc_methods.py
fasterpc/schemas.py
fasterpc/simplewebsocket.py
fasterpc/utils.py
fasterpc/websocket_rpc_client.py
fasterpc/websocket_rpc_endpoint.py
fasterpc-0.1.2.dist-info/METADATA
fasterpc-0.1.2.dist-info/WHEEL
fasterpc-0.1.2.dist-info/top_level.txt
fasterpc-0.1.2.dist-info/RECORD
