Metadata-Version: 2.4
Name: fasterpc
Version: 0.1.2
Summary: A fast and durable bidirectional JSON RPC channel over websockets and fastapi.
Home-page: https://github.com/SRSWTI/fasterpc
Author: SRSWTI Research Labs
Author-email: team@srswti.com
Classifier: Programming Language :: Python :: 3
Classifier: License :: OSI Approved :: MIT License
Classifier: Operating System :: OS Independent
Classifier: Topic :: Internet :: WWW/HTTP :: HTTP Servers
Classifier: Topic :: Internet :: WWW/HTTP :: WSGI
Requires-Python: >=3.9
Requires-Dist: fastapi<1,>=0.109.1
Requires-Dist: packaging>=20.4
Requires-Dist: pydantic>=1.9.1
Requires-Dist: websockets>=10.3
Requires-Dist: tenacity>=8.0.1
Provides-Extra: websocket-client
Requires-Dist: websocket-client>=1.1.0; extra == "websocket-client"
Dynamic: author
Dynamic: author-email
Dynamic: classifier
Dynamic: description
Dynamic: description-content-type
Dynamic: home-page
Dynamic: provides-extra
Dynamic: requires-dist
Dynamic: requires-python
Dynamic: summary
